.gitignore
.travis.yml
HISTORY.rst
LICENSE
README.rst
TODO.rst
setup.cfg
setup.py
FreqDemod.egg-info/PKG-INFO
FreqDemod.egg-info/SOURCES.txt
FreqDemod.egg-info/dependency_links.txt
FreqDemod.egg-info/not-zip-safe
FreqDemod.egg-info/requires.txt
FreqDemod.egg-info/top_level.txt
docs/Makefile
docs/acknow.rst
docs/background.rst
docs/background1.rst
docs/background2.rst
docs/background3.rst
docs/conf.py
docs/demodulate.rst
docs/develop.rst
docs/fabfile.py
docs/hdf5.rst
docs/history.rst
docs/index.rst
docs/intro.rst
docs/license.rst
docs/quickstart.rst
docs/tests.rst
docs/util.rst
freqdemod/__init__.py
freqdemod/demodulate.py
freqdemod/util.py
freqdemod/docs/JAM_9p90__copy.h5
freqdemod/docs/freqdemod-derivation.nb
freqdemod/docs/freqdemod-derivation.pdf
freqdemod/docs/freqdemod-develop-obsolete-1.ipynb
freqdemod/docs/freqdemod-develop-obsolete-2.ipynb
freqdemod/docs/freqdemod-develop-obsolete-3.ipynb
freqdemod/docs/freqdemod-develop-obsolete-4.ipynb
freqdemod/docs/freqdemod-develop-obsolete-5.ipynb
freqdemod/docs/freqdemod-quickstart-1.ipynb
freqdemod/docs/output.wav
freqdemod/docs/play.py
freqdemod/docs/record.py
freqdemod/docs/scratch.ipynb
freqdemod/docs/wavplot.py
freqdemod/hdf5/__init__.py
freqdemod/hdf5/hdf5_util.py
freqdemod/tests/__init__.py
freqdemod/tests/test_freqdemod.py
freqdemod/tests/test_hdf5.py