Metadata-Version: 1.1
Name: FreqDemod
Version: 0.2.1
Summary: This package provides functions for analyzing and plotting the
Home-page: https://github.com/JohnMarohn/FreqDemod
Author: John Marohn
Author-email: jam99@cornell.edu
License: GPLv3
Platform: UNKNOWN
Classifier: Development Status :: 4 - Beta
Classifier: License :: OSI Approved :: GNU Lesser General Public License v3 (LGPLv3)
Classifier: Intended Audience :: Science/Research
Classifier: Natural Language :: English
Classifier: Programming Language :: Python :: 2
Classifier: Programming Language :: Python :: 2.7
